{
    "%vlocity_namespace%__Active__c": true,
    "%vlocity_namespace%__OmniScriptId__c": {
        "Name": "ESM_AsyncCreateQuoteMembersFromAssets",
        "VlocityDataPackType": "VlocityMatchingKeyObject",
        "VlocityMatchingRecordSourceKey": "%vlocity_namespace%__OmniScript__c/ESM/AsyncCreateQuoteMembersFromAssets/Procedure",
        "VlocityRecordSObjectType": "%vlocity_namespace%__OmniScript__c"
    },
    "%vlocity_namespace%__PropertySet__c": {
        "actionMessage": "",
        "additionalChainableResponse": {
        },
        "additionalInput": {
            "AccountToQuoteMemberFieldMap": {
                "%vlocity_namespace%__BillingEmailAddress__c": "%vlocity_namespace%__Email__c",
                "Id": "%vlocity_namespace%__ServiceAccountId__c",
                "Name": "Name",
                "RecordTypeId": "%vlocity_namespace%__MemberType__c",
                "ShippingCity": "%vlocity_namespace%__City__c",
                "ShippingCountry": "%vlocity_namespace%__Country__c",
                "ShippingPostalCode": "%vlocity_namespace%__PostalCode__c",
                "ShippingState": "%vlocity_namespace%__State__c",
                "ShippingStreet": "%vlocity_namespace%__StreetAddress__c"
            },
            "additionalQuoteMemberData": "%additionalData:additionalQuoteMemberData%",
            "assetIds": "%itemsToProcessSubsetList%",
            "checkDuplicateWithCreatedQM": true,
            "quoteId": "%additionalData:QuoteId%"
        },
        "additionalOutput": {
        },
        "chainOnStep": false,
        "disOnTplt": false,
        "executionConditionalFormula": "",
        "failOnStepError": true,
        "failureConditionalFormula": "",
        "failureResponse": {
        },
        "label": "RemoteAction1",
        "remoteClass": "B2BCmexAppHandler",
        "remoteMethod": "createQuoteMembersFromAssets",
        "remoteOptions": {
        },
        "responseJSONNode": "",
        "responseJSONPath": "",
        "returnOnlyAdditionalOutput": false,
        "returnOnlyFailureResponse": false,
        "sendJSONNode": "",
        "sendJSONPath": "",
        "sendOnlyAdditionalInput": true,
        "show": null,
        "useFormulas": true
    },
    "%vlocity_namespace%__ReusableOmniScript__c": false,
    "%vlocity_namespace%__Type__c": "Remote Action",
    "Name": "createQuoteMembers",
    "VlocityDataPackType": "SObject",
    "VlocityRecordSObjectType": "%vlocity_namespace%__Element__c",
    "VlocityRecordSourceKey": "%vlocity_namespace%__Element__c/%vlocity_namespace%__OmniScript__c/ESM/AsyncCreateQuoteMembersFromAssets/Procedure/createQuoteMembers"
}