[
    {
        "%vlocity_namespace%__DomainObjectAPIName__c": "json",
        "%vlocity_namespace%__DomainObjectCreationOrder__c": 0,
        "%vlocity_namespace%__DomainObjectFieldAPIName__c": "order",
        "%vlocity_namespace%__FilterGroup__c": 0,
        "%vlocity_namespace%__FilterOperator__c": "=",
        "%vlocity_namespace%__FilterValue__c": "OrderId",
        "%vlocity_namespace%__GlobalKey__c": "ef593da9-3780-ed00-c0d1-8d1947fe70c0",
        "%vlocity_namespace%__InterfaceFieldAPIName__c": "%vlocity_namespace%__Order",
        "%vlocity_namespace%__InterfaceObjectLookupOrder__c": 1,
        "%vlocity_namespace%__InterfaceObjectName__c": "%vlocity_namespace%__OrderMember__c",
        "%vlocity_namespace%__IsDisabled__c": false,
        "%vlocity_namespace%__IsRequiredForUpsert__c": false,
        "%vlocity_namespace%__MapId__c": "GetEsmServiceAccountFromOrderLineItem5471798080529908",
        "%vlocity_namespace%__OMplusSyncEnabled__c": true,
        "%vlocity_namespace%__UpsertKey__c": false,
        "Name": "GetEsmServiceAccountFromOrderLineItem",
        "VlocityDataPackType": "SObject",
        "VlocityRecordSObjectType": "%vlocity_namespace%__DRMapItem__c"
    },
    {
        "%vlocity_namespace%__DomainObjectAPIName__c": "json",
        "%vlocity_namespace%__DomainObjectCreationOrder__c": 0,
        "%vlocity_namespace%__DomainObjectFieldAPIName__c": "order",
        "%vlocity_namespace%__FilterGroup__c": 0,
        "%vlocity_namespace%__FilterOperator__c": "=",
        "%vlocity_namespace%__FilterValue__c": "ServiceAccountId",
        "%vlocity_namespace%__GlobalKey__c": "21b7a081-403e-bb9e-5326-885cf469dcf6",
        "%vlocity_namespace%__InterfaceFieldAPIName__c": "%vlocity_namespace%__ServiceAccountId__c",
        "%vlocity_namespace%__InterfaceObjectLookupOrder__c": 1,
        "%vlocity_namespace%__InterfaceObjectName__c": "%vlocity_namespace%__OrderMember__c",
        "%vlocity_namespace%__IsDisabled__c": false,
        "%vlocity_namespace%__IsRequiredForUpsert__c": false,
        "%vlocity_namespace%__MapId__c": "GetEsmServiceAccountFromOrderLineItem43276194227163445",
        "%vlocity_namespace%__OMplusSyncEnabled__c": true,
        "%vlocity_namespace%__UpsertKey__c": false,
        "Name": "GetEsmServiceAccountFromOrderLineItem",
        "VlocityDataPackType": "SObject",
        "VlocityRecordSObjectType": "%vlocity_namespace%__DRMapItem__c"
    },
    {
        "%vlocity_namespace%__DomainObjectAPIName__c": "json",
        "%vlocity_namespace%__DomainObjectCreationOrder__c": 1,
        "%vlocity_namespace%__DomainObjectFieldAPIName__c": "City",
        "%vlocity_namespace%__GlobalKey__c": "dc4f5e64-66f7-fdd4-b849-c196fe52721a",
        "%vlocity_namespace%__InterfaceFieldAPIName__c": "order:%vlocity_namespace%__City__c",
        "%vlocity_namespace%__IsDisabled__c": false,
        "%vlocity_namespace%__IsRequiredForUpsert__c": false,
        "%vlocity_namespace%__MapId__c": "GetEsmServiceAccountFromOrderLineItem958935714601771",
        "%vlocity_namespace%__OMplusSyncEnabled__c": true,
        "%vlocity_namespace%__UpsertKey__c": false,
        "Name": "GetEsmServiceAccountFromOrderLineItem",
        "VlocityDataPackType": "SObject",
        "VlocityRecordSObjectType": "%vlocity_namespace%__DRMapItem__c"
    },
    {
        "%vlocity_namespace%__DomainObjectAPIName__c": "json",
        "%vlocity_namespace%__DomainObjectCreationOrder__c": 1,
        "%vlocity_namespace%__DomainObjectFieldAPIName__c": "Country",
        "%vlocity_namespace%__GlobalKey__c": "3c8e71a0-e03c-d8ea-12e0-5a637a57bbe1",
        "%vlocity_namespace%__InterfaceFieldAPIName__c": "order:%vlocity_namespace%__Country__c",
        "%vlocity_namespace%__IsDisabled__c": false,
        "%vlocity_namespace%__IsRequiredForUpsert__c": false,
        "%vlocity_namespace%__MapId__c": "GetEsmServiceAccountFromOrderLineItem17902347071557934",
        "%vlocity_namespace%__OMplusSyncEnabled__c": true,
        "%vlocity_namespace%__UpsertKey__c": false,
        "Name": "GetEsmServiceAccountFromOrderLineItem",
        "VlocityDataPackType": "SObject",
        "VlocityRecordSObjectType": "%vlocity_namespace%__DRMapItem__c"
    },
    {
        "%vlocity_namespace%__DomainObjectAPIName__c": "json",
        "%vlocity_namespace%__DomainObjectCreationOrder__c": 1,
        "%vlocity_namespace%__DomainObjectFieldAPIName__c": "Name",
        "%vlocity_namespace%__GlobalKey__c": "e7993563-066d-b64b-4188-525a04f6baf7",
        "%vlocity_namespace%__InterfaceFieldAPIName__c": "order:Name",
        "%vlocity_namespace%__IsDisabled__c": false,
        "%vlocity_namespace%__IsRequiredForUpsert__c": false,
        "%vlocity_namespace%__MapId__c": "GetEsmServiceAccountFromOrderLineItem894644490472887",
        "%vlocity_namespace%__OMplusSyncEnabled__c": true,
        "%vlocity_namespace%__UpsertKey__c": false,
        "Name": "GetEsmServiceAccountFromOrderLineItem",
        "VlocityDataPackType": "SObject",
        "VlocityRecordSObjectType": "%vlocity_namespace%__DRMapItem__c"
    },
    {
        "%vlocity_namespace%__DomainObjectAPIName__c": "json",
        "%vlocity_namespace%__DomainObjectCreationOrder__c": 1,
        "%vlocity_namespace%__DomainObjectFieldAPIName__c": "PostalCode",
        "%vlocity_namespace%__GlobalKey__c": "e606d87f-e6ab-220f-8316-268b8ba97ed4",
        "%vlocity_namespace%__InterfaceFieldAPIName__c": "order:%vlocity_namespace%__PostalCode__c",
        "%vlocity_namespace%__IsDisabled__c": false,
        "%vlocity_namespace%__IsRequiredForUpsert__c": false,
        "%vlocity_namespace%__MapId__c": "GetEsmServiceAccountFromOrderLineItem2633515129634365",
        "%vlocity_namespace%__OMplusSyncEnabled__c": true,
        "%vlocity_namespace%__UpsertKey__c": false,
        "Name": "GetEsmServiceAccountFromOrderLineItem",
        "VlocityDataPackType": "SObject",
        "VlocityRecordSObjectType": "%vlocity_namespace%__DRMapItem__c"
    },
    {
        "%vlocity_namespace%__DomainObjectAPIName__c": "json",
        "%vlocity_namespace%__DomainObjectCreationOrder__c": 1,
        "%vlocity_namespace%__DomainObjectFieldAPIName__c": "QuoteMemberId",
        "%vlocity_namespace%__GlobalKey__c": "9058a12f-59b5-508c-8e04-1b07a9839b45",
        "%vlocity_namespace%__InterfaceFieldAPIName__c": "order:Id",
        "%vlocity_namespace%__IsDisabled__c": false,
        "%vlocity_namespace%__IsRequiredForUpsert__c": false,
        "%vlocity_namespace%__MapId__c": "GetEsmServiceAccountFromOrderLineItem36109904761637757",
        "%vlocity_namespace%__OMplusSyncEnabled__c": true,
        "%vlocity_namespace%__UpsertKey__c": false,
        "Name": "GetEsmServiceAccountFromOrderLineItem",
        "VlocityDataPackType": "SObject",
        "VlocityRecordSObjectType": "%vlocity_namespace%__DRMapItem__c"
    },
    {
        "%vlocity_namespace%__DomainObjectAPIName__c": "json",
        "%vlocity_namespace%__DomainObjectCreationOrder__c": 1,
        "%vlocity_namespace%__DomainObjectFieldAPIName__c": "State",
        "%vlocity_namespace%__GlobalKey__c": "f9f98a75-c175-ef53-4665-e4e648d3c6d4",
        "%vlocity_namespace%__InterfaceFieldAPIName__c": "order:%vlocity_namespace%__State__c",
        "%vlocity_namespace%__IsDisabled__c": false,
        "%vlocity_namespace%__IsRequiredForUpsert__c": false,
        "%vlocity_namespace%__MapId__c": "GetEsmServiceAccountFromOrderLineItem08690666635351274",
        "%vlocity_namespace%__OMplusSyncEnabled__c": true,
        "%vlocity_namespace%__UpsertKey__c": false,
        "Name": "GetEsmServiceAccountFromOrderLineItem",
        "VlocityDataPackType": "SObject",
        "VlocityRecordSObjectType": "%vlocity_namespace%__DRMapItem__c"
    },
    {
        "%vlocity_namespace%__DomainObjectAPIName__c": "json",
        "%vlocity_namespace%__DomainObjectCreationOrder__c": 1,
        "%vlocity_namespace%__DomainObjectFieldAPIName__c": "StreetAddress",
        "%vlocity_namespace%__GlobalKey__c": "d5cf382e-d1b1-bbbc-8b31-9998e36804a0",
        "%vlocity_namespace%__InterfaceFieldAPIName__c": "order:%vlocity_namespace%__StreetAddress__c",
        "%vlocity_namespace%__IsDisabled__c": false,
        "%vlocity_namespace%__IsRequiredForUpsert__c": false,
        "%vlocity_namespace%__MapId__c": "GetEsmServiceAccountFromOrderLineItem9313990289369869",
        "%vlocity_namespace%__OMplusSyncEnabled__c": true,
        "%vlocity_namespace%__UpsertKey__c": false,
        "Name": "GetEsmServiceAccountFromOrderLineItem",
        "VlocityDataPackType": "SObject",
        "VlocityRecordSObjectType": "%vlocity_namespace%__DRMapItem__c"
    },
    {
        "%vlocity_namespace%__DomainObjectAPIName__c": "json",
        "%vlocity_namespace%__DomainObjectCreationOrder__c": 1,
        "%vlocity_namespace%__DomainObjectFieldAPIName__c": "sid",
        "%vlocity_namespace%__GlobalKey__c": "2212e209-ecad-195a-a908-acd0947883c5",
        "%vlocity_namespace%__InterfaceFieldAPIName__c": "order:%vlocity_namespace%__ServiceAccountId__c",
        "%vlocity_namespace%__IsDisabled__c": false,
        "%vlocity_namespace%__IsRequiredForUpsert__c": false,
        "%vlocity_namespace%__MapId__c": "GetEsmServiceAccountFromOrderLineItem896104011911004",
        "%vlocity_namespace%__OMplusSyncEnabled__c": true,
        "%vlocity_namespace%__UpsertKey__c": false,
        "Name": "GetEsmServiceAccountFromOrderLineItem",
        "VlocityDataPackType": "SObject",
        "VlocityRecordSObjectType": "%vlocity_namespace%__DRMapItem__c"
    }
]