[
    {
        "%vlocity_namespace%__DefaultValue__c": "''",
        "%vlocity_namespace%__DomainObjectAPIName__c": "json",
        "%vlocity_namespace%__DomainObjectCreationOrder__c": 1,
        "%vlocity_namespace%__DomainObjectFieldAPIName__c": "%vlocity_namespace%__AsyncOperation__c",
        "%vlocity_namespace%__GlobalKey__c": "60026913-9a6e-4ba6-d026-03038835b7a1",
        "%vlocity_namespace%__InterfaceFieldAPIName__c": "asyncOperation",
        "%vlocity_namespace%__IsDisabled__c": false,
        "%vlocity_namespace%__IsRequiredForUpsert__c": false,
        "%vlocity_namespace%__MapId__c": "ESMCreateQuoteRequestDataCustoma00Dn000008fkIiIAIItem2",
        "%vlocity_namespace%__OMplusSyncEnabled__c": true,
        "%vlocity_namespace%__TransformValuesMap__c": "{\"asyncOperation\":\"''\"}",
        "%vlocity_namespace%__UpsertKey__c": false,
        "Name": "ESMCreateQuoteRequestData",
        "VlocityDataPackType": "SObject",
        "VlocityRecordSObjectType": "%vlocity_namespace%__DRMapItem__c"
    },
    {
        "%vlocity_namespace%__DomainObjectAPIName__c": "json",
        "%vlocity_namespace%__DomainObjectCreationOrder__c": 1,
        "%vlocity_namespace%__DomainObjectFieldAPIName__c": "%vlocity_namespace%__pricelistid__c",
        "%vlocity_namespace%__GlobalKey__c": "8ce07f50-271f-b078-481f-c786df9c771e",
        "%vlocity_namespace%__InterfaceFieldAPIName__c": "createQuotePriceList",
        "%vlocity_namespace%__IsDisabled__c": false,
        "%vlocity_namespace%__IsRequiredForUpsert__c": false,
        "%vlocity_namespace%__MapId__c": "ESMCreateQuoteRequestDataCustoma00Dn000008fkIiIAIItem3",
        "%vlocity_namespace%__OMplusSyncEnabled__c": true,
        "%vlocity_namespace%__UpsertKey__c": false,
        "Name": "ESMCreateQuoteRequestData",
        "VlocityDataPackType": "SObject",
        "VlocityRecordSObjectType": "%vlocity_namespace%__DRMapItem__c"
    },
    {
        "%vlocity_namespace%__DomainObjectAPIName__c": "json",
        "%vlocity_namespace%__DomainObjectCreationOrder__c": 1,
        "%vlocity_namespace%__DomainObjectFieldAPIName__c": "AccountId",
        "%vlocity_namespace%__GlobalKey__c": "7ea96d4a-07c8-6f0d-87f0-3f9f8cd02562",
        "%vlocity_namespace%__InterfaceFieldAPIName__c": "ContextId",
        "%vlocity_namespace%__IsDisabled__c": false,
        "%vlocity_namespace%__IsRequiredForUpsert__c": false,
        "%vlocity_namespace%__MapId__c": "ESMCreateQuoteRequestDataCustoma00Dn000008fkIiIAIItem4",
        "%vlocity_namespace%__OMplusSyncEnabled__c": true,
        "%vlocity_namespace%__UpsertKey__c": false,
        "Name": "ESMCreateQuoteRequestData",
        "VlocityDataPackType": "SObject",
        "VlocityRecordSObjectType": "%vlocity_namespace%__DRMapItem__c"
    },
    {
        "%vlocity_namespace%__DomainObjectAPIName__c": "json",
        "%vlocity_namespace%__DomainObjectCreationOrder__c": 1,
        "%vlocity_namespace%__DomainObjectFieldAPIName__c": "OpportunityId",
        "%vlocity_namespace%__GlobalKey__c": "71eea295-3809-3fb0-218e-71e3f113a298",
        "%vlocity_namespace%__InterfaceFieldAPIName__c": "opportunityId",
        "%vlocity_namespace%__IsDisabled__c": false,
        "%vlocity_namespace%__IsRequiredForUpsert__c": false,
        "%vlocity_namespace%__MapId__c": "ESMCreateQuoteRequestDataCustoma00Dn000008fkIiIAIItem5",
        "%vlocity_namespace%__OMplusSyncEnabled__c": true,
        "%vlocity_namespace%__UpsertKey__c": false,
        "Name": "ESMCreateQuoteRequestData",
        "VlocityDataPackType": "SObject",
        "VlocityRecordSObjectType": "%vlocity_namespace%__DRMapItem__c"
    },
    {
        "%vlocity_namespace%__DomainObjectAPIName__c": "json",
        "%vlocity_namespace%__DomainObjectCreationOrder__c": 1,
        "%vlocity_namespace%__DomainObjectFieldAPIName__c": "name",
        "%vlocity_namespace%__GlobalKey__c": "b57e16c4-bee3-111b-871f-be277cddae05",
        "%vlocity_namespace%__InterfaceFieldAPIName__c": "quoteName",
        "%vlocity_namespace%__IsDisabled__c": false,
        "%vlocity_namespace%__IsRequiredForUpsert__c": false,
        "%vlocity_namespace%__MapId__c": "ESMCreateQuoteRequestDataCustoma00Dn000008fkIiIAIItem6",
        "%vlocity_namespace%__OMplusSyncEnabled__c": true,
        "%vlocity_namespace%__UpsertKey__c": false,
        "Name": "ESMCreateQuoteRequestData",
        "VlocityDataPackType": "SObject",
        "VlocityRecordSObjectType": "%vlocity_namespace%__DRMapItem__c"
    },
    {
        "%vlocity_namespace%__DefaultValue__c": "EnterpriseQuote",
        "%vlocity_namespace%__DomainObjectAPIName__c": "json",
        "%vlocity_namespace%__DomainObjectCreationOrder__c": 1,
        "%vlocity_namespace%__DomainObjectFieldAPIName__c": "recordType",
        "%vlocity_namespace%__GlobalKey__c": "b4446983-e43c-db49-e970-41ff5aa70564",
        "%vlocity_namespace%__InterfaceFieldAPIName__c": "quoteRecordType",
        "%vlocity_namespace%__IsDisabled__c": false,
        "%vlocity_namespace%__IsRequiredForUpsert__c": false,
        "%vlocity_namespace%__MapId__c": "ESMCreateQuoteRequestDataCustoma00Dn000008fkIiIAIItem7",
        "%vlocity_namespace%__OMplusSyncEnabled__c": true,
        "%vlocity_namespace%__TransformValuesMap__c": "{\"qutoeRecordType\":\"EnterpriseQuote\"}",
        "%vlocity_namespace%__UpsertKey__c": false,
        "Name": "ESMCreateQuoteRequestData",
        "VlocityDataPackType": "SObject",
        "VlocityRecordSObjectType": "%vlocity_namespace%__DRMapItem__c"
    }
]